vedro_openapi_testgen/__init__.py
vedro_openapi_testgen/__version__.py
vedro_openapi_testgen/command.py
vedro_openapi_testgen/py.typed
vedro_openapi_testgen-0.0.3.dist-info/METADATA
vedro_openapi_testgen-0.0.3.dist-info/WHEEL
vedro_openapi_testgen-0.0.3.dist-info/entry_points.txt
vedro_openapi_testgen-0.0.3.dist-info/top_level.txt
vedro_openapi_testgen-0.0.3.dist-info/RECORD
